garbagetruck/__init__.py
garbagetruck/cli.py
garbagetruck/garbagetruck.py
garbagetruck-0.1.0.dist-info/DESCRIPTION.rst
garbagetruck-0.1.0.dist-info/METADATA
garbagetruck-0.1.0.dist-info/RECORD
garbagetruck-0.1.0.dist-info/WHEEL
garbagetruck-0.1.0.dist-info/entry_points.txt
garbagetruck-0.1.0.dist-info/metadata.json
garbagetruck-0.1.0.dist-info/top_level.txt
