Metadata-Version: 2.0
Name: garbagetruck
Version: 0.1.0
Summary: A small tool to periodically move old files into the local file system trash.
Home-page: https://github.com/bradrf/garbagetruck
Author: Brad Robel-Forrest
Author-email: brad@bitpony.com
License: MIT license
Keywords: garbagetruck
Platform: UNKNOWN
Classifier: Development Status :: 2 - Pre-Alpha
Classifier: Intended Audience :: Developers
Classifier: License :: OSI Approved :: MIT License
Classifier: Natural Language :: English
Classifier: Programming Language :: Python :: 2
Classifier: Programming Language :: Python :: 2.6
Classifier: Programming Language :: Python :: 2.7
Classifier: Programming Language :: Python :: 3
Classifier: Programming Language :: Python :: 3.3
Classifier: Programming Language :: Python :: 3.4
Classifier: Programming Language :: Python :: 3.5
Requires-Dist: Click (>=6.0)
Requires-Dist: future (>=0.15.2)
Requires-Dist: python-crontab (>=2.1.1)
Requires-Dist: send2trash (>=1.3.0)
